django_rsync_storage-0.0.5.dist-info/DESCRIPTION.rst
django_rsync_storage-0.0.5.dist-info/METADATA
django_rsync_storage-0.0.5.dist-info/RECORD
django_rsync_storage-0.0.5.dist-info/WHEEL
django_rsync_storage-0.0.5.dist-info/metadata.json
django_rsync_storage-0.0.5.dist-info/top_level.txt
rsync_storage/__init__.py
rsync_storage/rsync.py
rsync_storage/settings.rsync_sample.py
rsync_storage/settings_rsync_sample.py
rsync_storage/tasks.py
