Metadata-Version: 2.0
Name: django-rsync-storage
Version: 0.0.5
Summary: Django storage for rsync distributive copy of files
Home-page: https://github.com/g10k/django-rsync-storage
Author: Sergey Vlasov
Author-email: g10k.info@gmail.com
License: BSD License
Platform: UNKNOWN
Classifier: Environment :: Web Environment
Classifier: Framework :: Django
Classifier: Framework :: Django :: 1.9
Classifier: Intended Audience :: Developers
Classifier: License :: OSI Approved :: BSD License
Classifier: Operating System :: OS Independent
Classifier: Programming Language :: Python
Classifier: Programming Language :: Python :: 2.7
Classifier: Topic :: Internet :: WWW/HTTP
Classifier: Topic :: Internet :: WWW/HTTP :: Dynamic Content
Requires-Dist: celery (>=3.1.18)
